pvvoltloss/__init__.py
pvvoltloss/__main__.py
pvvoltloss/cli.py
pvvoltloss/config.py
pvvoltloss/data_handler.py
pvvoltloss/gui.py
pvvoltloss/nogui.py
pvvoltloss/physics.py
pvvoltloss/plotting.py
pvvoltloss/data/solarSpectrum.csv
pvvoltloss/data/examples/example_EL.csv
pvvoltloss/data/examples/example_EQE.csv
pvvoltloss-1.0.0.dist-info/licenses/LICENSE
pvvoltloss-1.0.0.dist-info/METADATA
pvvoltloss-1.0.0.dist-info/WHEEL
pvvoltloss-1.0.0.dist-info/entry_points.txt
pvvoltloss-1.0.0.dist-info/top_level.txt
pvvoltloss-1.0.0.dist-info/RECORD
