Metadata-Version: 2.4
Name: pvvoltloss
Version: 1.0.0
Summary: Tools for pv voltage loss analysis using EQE and EL spectra.
Author: Jolanda S. Müller
License: BSD 3-Clause License
Project-URL: Homepage, https://github.com/Jenny-Nelson-Group/pvvoltloss
Project-URL: Issues, https://github.com/Jenny-Nelson-Group/pvvoltloss
Keywords: photovoltaics,opv,voltage losses,eqe,electroluminescence,reciprocity
Classifier: Development Status :: 3 - Alpha
Classifier: Intended Audience :: Science/Research
Classifier: License :: OSI Approved :: BSD License
Classifier: Programming Language :: Python :: 3
Classifier: Programming Language :: Python :: 3 :: Only
Classifier: Programming Language :: Python :: 3.9
Classifier: Programming Language :: Python :: 3.10
Classifier: Programming Language :: Python :: 3.11
Classifier: Programming Language :: Python :: 3.12
Classifier: Topic :: Scientific/Engineering
Requires-Python: >=3.9
License-File: LICENSE
Requires-Dist: matplotlib>=3.10.0
Requires-Dist: numpy>=2.3.0
Requires-Dist: pandas>=2.3.0
Requires-Dist: scipy>=1.16.2
Requires-Dist: openpyxl>=3.1
Requires-Dist: xlrd>=2.0
Dynamic: license-file
